elapi/.DS_Store
elapi/VERSION
elapi/__init__.py
elapi/_core_init/__init__.py
elapi/_core_init/_cache.py
elapi/_core_init/_loggers/__init__.py
elapi/_core_init/_loggers/base.py
elapi/_core_init/_loggers/handlers/__init__.py
elapi/_core_init/_loggers/handlers/base.py
elapi/_core_init/_loggers/handlers/callback.py
elapi/_core_init/_loggers/handlers/stderr.py
elapi/_core_init/_utils.py
elapi/_names.py
elapi/_vendor/__init__.py
elapi/_vendor/haggis/LICENSE
elapi/_vendor/haggis/__init__.py
elapi/_vendor/haggis/logs.py
elapi/_vendor/haggis/version.py
elapi/api/__init__.py
elapi/api/_handle_unexp_response.py
elapi/api/_names.py
elapi/api/_openapi_parser.py
elapi/api/_supported_versions/5.1.15.json
elapi/api/_supported_versions/5.2.0.json
elapi/api/_supported_versions/5.2.1.json
elapi/api/_supported_versions/5.2.2.json
elapi/api/_supported_versions/5.2.3.json
elapi/api/_supported_versions/5.2.4.json
elapi/api/_supported_versions/5.2.5.json
elapi/api/_supported_versions/5.2.6.json
elapi/api/_supported_versions/5.2.7.json
elapi/api/_supported_versions/5.2.8.json
elapi/api/_supported_versions/5.3.0.json
elapi/api/_supported_versions/5.3.1.json
elapi/api/_supported_versions/5.3.2.json
elapi/api/_supported_versions/5.3.3.json
elapi/api/_supported_versions/5.3.4.json
elapi/api/_supported_versions/5.3.5.json
elapi/api/_supported_versions/5.3.6.json
elapi/api/_supported_versions/5.3.7.json
elapi/api/api.py
elapi/api/endpoint.py
elapi/api/validators.py
elapi/cli/__init__.py
elapi/cli/__main__.py
elapi/cli/_plugin_handler.py
elapi/cli/_venv_state_manager.py
elapi/cli/doc.py
elapi/cli/elapi.py
elapi/configuration/__init__.py
elapi/configuration/_config_history.py
elapi/configuration/_overload_history.py
elapi/configuration/config.py
elapi/configuration/overridable_vars.py
elapi/configuration/validators.py
elapi/core_validators/__init__.py
elapi/core_validators/base.py
elapi/core_validators/path.py
elapi/loggers/__init__.py
elapi/loggers/base.py
elapi/loggers/handlers/__init__.py
elapi-2.4.6.dist-info/licenses/LICENSE
elapi-2.4.6.dist-info/licenses/src/elapi/_vendor/__init__.py
elapi-2.4.6.dist-info/licenses/src/elapi/_vendor/haggis/LICENSE
elapi-2.4.6.dist-info/WHEEL
elapi-2.4.6.dist-info/entry_points.txt
elapi-2.4.6.dist-info/METADATA
elapi-2.4.6.dist-info/RECORD
