Metadata-Version: 2.4
Name: elapi
Version: 2.4.6
Summary: elAPI is a powerful, extensible API client for eLabFTW.
Keywords: elabftw,api
Author: Alexander Haller, Mahadi Xion
Author-email: Alexander Haller, Mahadi Xion <elabftw@uni-heidelberg.de>
License-Expression: AGPL-3.0-only
License-File: LICENSE
License-File: src/elapi/_vendor/__init__.py
License-File: src/elapi/_vendor/haggis/LICENSE
Classifier: Development Status :: 5 - Production/Stable
Classifier: Framework :: AnyIO
Classifier: Framework :: AsyncIO
Classifier: Intended Audience :: Developers
Classifier: Intended Audience :: System Administrators
Classifier: Natural Language :: English
Classifier: Operating System :: OS Independent
Classifier: Topic :: Internet :: WWW/HTTP
Classifier: Topic :: Software Development :: Libraries :: Python Modules
Classifier: Topic :: System :: Systems Administration
Classifier: Topic :: Utilities
Requires-Dist: dynaconf>=3.2.0,<4
Requires-Dist: httpx[http2]>=0.28.1,<0.29
Requires-Dist: httpx-auth>=0.23.1,<0.24
Requires-Dist: rich>=13.8.0,<14
Requires-Dist: typer[all]>=0.9.0,<0.10
Requires-Dist: pyyaml==6.0.2
Requires-Dist: mistune==3.1.3
Requires-Dist: click>=8.1.8,<8.2
Requires-Dist: httpx-limiter>=0.3.0,<0.4.0
Requires-Dist: httpx-aiohttp>=0.1.8,<0.2
Requires-Dist: pydantic>=2.12.3
Requires-Dist: jinja2>=3.1.6,<3.2 ; extra == 'mail'
Requires-Dist: nameparser>=1.1.3 ; extra == 'mail'
Requires-Dist: yagmail>=0.15.293,<0.16 ; extra == 'mail'
Requires-Dist: python-dateutil>=2.9.0.post0,<3 ; extra == 'uhd-urz'
Requires-Dist: tenacity>=9.1.2,<10 ; extra == 'uhd-urz'
Requires-Dist: uvloop>=0.21.0,<0.22 ; extra == 'uhd-urz'
Maintainer: Mahadi Xion
Maintainer-email: Mahadi Xion <mahadi.xion@urz.uni-heidelberg.de>
Requires-Python: >=3.11.0, <4
Project-URL: Changelog, https://github.com/uhd-urz/elAPI/blob/main/CHANGELOG.md
Project-URL: Homepage, https://www.urz.uni-heidelberg.de/de/service-katalog/software-und-anwendungen/elabftw
Project-URL: Issues, https://github.com/uhd-urz/elAPI/issues
Project-URL: Repository, https://github.com/uhd-urz/elAPI.git
Provides-Extra: mail
Provides-Extra: uhd-urz
